README.md
pyproject.toml
toxicslave/__init__.py
toxicslave/build.py
toxicslave/cmds.py
toxicslave/docker.py
toxicslave/exceptions.py
toxicslave/managers.py
toxicslave/plugins.py
toxicslave/protocols.py
toxicslave/server.py
toxicslave.egg-info/PKG-INFO
toxicslave.egg-info/SOURCES.txt
toxicslave.egg-info/dependency_links.txt
toxicslave.egg-info/entry_points.txt
toxicslave.egg-info/requires.txt
toxicslave.egg-info/top_level.txt